MANIFEST.in
docs/Makefile
docs/_static/flask-oauthlib.png
docs/_templates/brand.html
docs/_templates/sidebarintro.html
docs/_themes/.git
docs/_themes/.gitignore
docs/_themes/LICENSE
docs/_themes/README
docs/_themes/flask/layout.html
docs/_themes/flask/relations.html
docs/_themes/flask/static/flasky.css_t
docs/_themes/flask/theme.conf
docs/_themes/flask_small/layout.html
docs/_themes/flask_small/static/flasky.css_t
docs/_themes/flask_small/theme.conf
docs/_themes/flask_theme_support.py
docs/additional.rst
docs/api.rst
docs/authors.rst
docs/changelog.rst
docs/client.rst
docs/conf.py
docs/contrib.rst
docs/index.rst
docs/install.rst
docs/intro.rst
docs/oauth1.rst
docs/oauth2.rst
example/contrib/experiment-client/douban.py
example/contrib/experiment-client/twitter.py
example/douban.py
example/dropbox.py
example/facebook.py
example/github.py
example/google.py
example/linkedin.py
example/oauth1_provider.py
example/oauth2_provider.py
example/qq.py
example/reddit.py
example/twitter.py
example/weibo.py
poetry.lock
pyproject.toml
sanic_oauthlib/__init__.py
sanic_oauthlib/client.py
sanic_oauthlib/contrib/__init__.py
sanic_oauthlib/contrib/apps.py
sanic_oauthlib/contrib/cache.py
sanic_oauthlib/contrib/oauth2.py
sanic_oauthlib/provider/__init__.py
sanic_oauthlib/provider/oauth1.py
sanic_oauthlib/provider/oauth2.py
sanic_oauthlib/utils.py
tests/__init__.py
tests/_base.py
tests/oauth1/__init__.py
tests/oauth1/client.py
tests/oauth1/server.py
tests/oauth1/test_oauth1.py
tests/oauth2/__init__.py
tests/oauth2/client.py
tests/oauth2/server.py
tests/oauth2/test_oauth2.py
tests/test_client.py
tests/test_contrib/__init__.py
tests/test_contrib/test_apps.py
tests/test_oauth2/__init__.py
tests/test_oauth2/base.py
tests/test_oauth2/test_client_credential.py
tests/test_oauth2/test_code.py
tests/test_oauth2/test_implicit.py
tests/test_oauth2/test_password.py
tests/test_oauth2/test_refresh.py
tests/test_utils.py
sanic_oauthlib-0.4.0.dist-info/entry_points.txt
sanic_oauthlib-0.4.0.dist-info/LICENSE
sanic_oauthlib-0.4.0.dist-info/WHEEL
sanic_oauthlib-0.4.0.dist-info/METADATA
sanic_oauthlib-0.4.0.dist-info/RECORD
