Metadata-Version: 2.1
Name: sanic-oauthlib
Version: 0.4.0
Summary: OAuthLib for Sanic, ported from Flask-OAuthLib
Home-page: https://github.com/ashleysommer/sanic_oauthlib
License: BSD
Author: Ashley Sommer
Author-email: ashleysommer@gmail.com
Requires-Python: >=3.7.0,<4.0.0
Classifier: Development Status :: 4 - Beta
Classifier: Environment :: Web Environment
Classifier: Intended Audience :: Developers
Classifier: License :: OSI Approved
Classifier: License :: OSI Approved :: BSD License
Classifier: License :: Other/Proprietary License
Classifier: Operating System :: POSIX
Classifier: Operating System :: POSIX :: Linux
Classifier: Programming Language :: Python
Classifier: Programming Language :: Python :: 3
Classifier: Programming Language :: Python :: 3 :: Only
Classifier: Programming Language :: Python :: 3.7
Classifier: Programming Language :: Python :: 3.8
Classifier: Programming Language :: Python :: 3.9
Classifier: Programming Language :: Python :: Implementation
Classifier: Programming Language :: Python :: Implementation :: CPython
Classifier: Programming Language :: Python :: Implementation :: PyPy
Classifier: Topic :: Internet :: WWW/HTTP :: Dynamic Content
Classifier: Topic :: Software Development :: Libraries :: Python Modules
Requires-Dist: httpx (>=0.9.3,<1.0.0)
Requires-Dist: oauthlib (==3.1.0)
Requires-Dist: sanic (>=21.3.4,<21.9)
Requires-Dist: sanic-plugin-toolkit (>=1.1.0)
Requires-Dist: sanic_session_sptk (>=0.6.0)
Project-URL: Repository, https://github.com/ashleysommer/sanic_oauthlib
